strongly_connected_components/__init__.py
strongly_connected_components/py.typed
strongly_connected_components/scc.py
strongly_connected_components-0.1.1.dist-info/METADATA
strongly_connected_components-0.1.1.dist-info/WHEEL
strongly_connected_components-0.1.1.dist-info/RECORD
